overscore.py
overscore-0.1.2.dist-info/LICENSE.txt
overscore-0.1.2.dist-info/METADATA
overscore-0.1.2.dist-info/WHEEL
overscore-0.1.2.dist-info/top_level.txt
overscore-0.1.2.dist-info/RECORD
