Metadata-Version: 2.1
Name: overscore
Version: 0.1.2
Summary: Double underscore access notation
Home-page: https://overscore.readthedocs.io/en/0.1.2/
Download-URL: https://github.com/gaf3/overscore
Author: Gaffer Fitch
Author-email: overscore@gaf3.com
Classifier: Programming Language :: Python :: 3
Classifier: License :: OSI Approved :: MIT License
License-File: LICENSE.txt
